wg_countdown_timer
