Metadata-Version: 2.1
Name: wg-countdown-timer
Version: 0.7.3
Summary: Worldman Games Countdown Timer
Home-page: https://gitlab.com/harry.sky.vortex/wgct
Author: Igor Nehoroshev
Author-email: mail@neigor.me
License: Apache License 2.0
Platform: UNKNOWN
Classifier: Development Status :: 3 - Alpha
Classifier: Environment :: Web Environment
Classifier: Intended Audience :: Developers
Classifier: License :: OSI Approved :: Apache Software License
Classifier: Operating System :: OS Independent
Classifier: Programming Language :: Python :: 3
Classifier: Programming Language :: Python :: 3.6
Classifier: Programming Language :: Python :: 3.7
Requires-Python: >=3.6
